boa/__init__.py
boa/abi.py
boa/builtins.py
boa/cli.py
boa/compiler.py
boa/util.py
boa/code/__init__.py
boa/code/action.py
boa/code/appcall.py
boa/code/ast_preprocess.py
boa/code/expression.py
boa/code/method.py
boa/code/module.py
boa/code/pyop.py
boa/code/pytoken.py
boa/code/vmtoken.py
boa/interop/BigInteger.py
boa/interop/SmartContract.py
boa/interop/VMOp.py
boa/interop/__init__.py
boa/interop/Neo/Account.py
boa/interop/Neo/Action.py
boa/interop/Neo/App.py
boa/interop/Neo/Asset.py
boa/interop/Neo/Attribute.py
boa/interop/Neo/Block.py
boa/interop/Neo/Blockchain.py
boa/interop/Neo/Contract.py
boa/interop/Neo/Enumerator.py
boa/interop/Neo/Header.py
boa/interop/Neo/Input.py
boa/interop/Neo/InvocationTransaction.py
boa/interop/Neo/Iterator.py
boa/interop/Neo/Output.py
boa/interop/Neo/Runtime.py
boa/interop/Neo/Storage.py
boa/interop/Neo/Transaction.py
boa/interop/Neo/TransactionType.py
boa/interop/Neo/TriggerType.py
boa/interop/Neo/Validator.py
boa/interop/Neo/Witness.py
boa/interop/Neo/__init__.py
boa/interop/System/ExecutionEngine.py
boa/interop/System/__init__.py
boa_test/__init__.py
boa_test/example/AbiMethods1.py
boa_test/example/AbiMethods2.py
boa_test/example/AbiMethods3.py
boa_test/example/AbiMethods4.py
boa_test/example/AbiMethods5.py
boa_test/example/AbiMethods6.py
boa_test/example/AbiMethods7.py
boa_test/example/AbiMethods8.py
boa_test/example/AddTest.py
boa_test/example/AddTest1.py
boa_test/example/AddTest2.py
boa_test/example/AddTest3.py
boa_test/example/AddTest4.py
boa_test/example/AddTestVoid.py
boa_test/example/AppendTest.py
boa_test/example/ArrayArgsTest.py
boa_test/example/ArrayRemoveTest.py
boa_test/example/ArrayReverseTest.py
boa_test/example/ArrayTest.py
boa_test/example/ArrayTest1.py
boa_test/example/ArrayTest2.py
boa_test/example/ArrayTest3.py
boa_test/example/ArrayTest4.py
boa_test/example/BinopTest.py
boa_test/example/BreakpointTest.py
boa_test/example/ByteArrayTest.py
neo_boa-0.7.2.dist-info/DESCRIPTION.rst
neo_boa-0.7.2.dist-info/METADATA
neo_boa-0.7.2.dist-info/RECORD
neo_boa-0.7.2.dist-info/WHEEL
neo_boa-0.7.2.dist-info/entry_points.txt
neo_boa-0.7.2.dist-info/metadata.json
neo_boa-0.7.2.dist-info/top_level.txt
