Metadata-Version: 2.0
Name: neo-boa
Version: 0.7.2
Summary: A Python compiler for the Neo Virtual Machine
Home-page: https://github.com/CityOfZion/neo-boa
Author: Thomas Saunders
Author-email: tasaunders@gmail.com
License: MIT
Keywords: compiler NEO .avm blockchain smartcontract development dApp
Platform: UNKNOWN
Classifier: Development Status :: 3 - Alpha
Classifier: Intended Audience :: Developers
Classifier: Topic :: Software Development :: Build Tools
Classifier: License :: OSI Approved :: MIT License
Classifier: Programming Language :: Python :: 3.6
Classifier: Programming Language :: Python :: 3.7
Requires-Python: >=3.6
Provides-Extra: dev
Provides-Extra: test
Requires-Dist: bytecode (==0.10.0)
Requires-Dist: astor
Requires-Dist: logzero (==1.5.0)
Provides-Extra: dev
Requires-Dist: twine; extra == 'dev'
Requires-Dist: wheel; extra == 'dev'
Requires-Dist: sphinx; extra == 'dev'
Requires-Dist: autopep8; extra == 'dev'
Requires-Dist: pep8; extra == 'dev'
Requires-Dist: sphinx-rtd-theme; extra == 'dev'
Provides-Extra: test
Requires-Dist: coverage; extra == 'test'
